docker/ci-runner/Dockerfile
docker/lofar_lotus/Dockerfile
docs/cleanup.py
docs/requirements.txt
docs/source/conf.py
docs/source/index.rst
docs/source/readme.rst
docs/source/static/css/custom.css
lofar_lotus/__init__.py
lofar_lotus/_version.py
lofar_lotus/dict/__init__.py
lofar_lotus/dict/_case_insensitive_dict.py
lofar_lotus/dict/_case_insensitive_string.py
lofar_lotus/file_access/README.md
lofar_lotus/file_access/__init__.py
lofar_lotus/file_access/_attribute_def.py
lofar_lotus/file_access/_lazy_dict.py
lofar_lotus/file_access/_member_def.py
lofar_lotus/file_access/_monitoring.py
lofar_lotus/file_access/_readers.py
lofar_lotus/file_access/_utils.py
lofar_lotus/file_access/_writers.py
lofar_lotus/file_access/hdf/__init__.py
lofar_lotus/file_access/hdf/_hdf5_utils.py
lofar_lotus/file_access/hdf/_hdf_readers.py
lofar_lotus/file_access/hdf/_hdf_writers.py
lofar_lotus/instrument/__init__.py
lofar_lotus/instrument/baseline.py
lofar_lotus/instrument/constants.py
lofar_lotus/instrument/station_constants.py
lofar_lotus/metrics/__init__.py
lofar_lotus/metrics/_decorators.py
lofar_lotus/metrics/_metrics.py
lofar_lotus/zeromq/__init__.py
lofar_lotus/zeromq/_pipe.py
lofar_lotus/zeromq/_publisher.py
lofar_lotus/zeromq/_subscriber.py
lofar_lotus-0.0.13.dist-info/licenses/LICENSE
lofar_lotus-0.0.13.dist-info/METADATA
lofar_lotus-0.0.13.dist-info/WHEEL
lofar_lotus-0.0.13.dist-info/top_level.txt
lofar_lotus-0.0.13.dist-info/RECORD
