Metadata-Version: 2.4
Name: lofar-lotus
Version: 0.0.13
Summary: Lots of things used somewhere
License-Expression: Apache-2.0
Project-URL: homepage, https://git.astron.nl/lofar2.0/lotus
Classifier: Development Status :: 3 - Alpha
Classifier: Environment :: Console
Classifier: Intended Audience :: Developers
Classifier: Intended Audience :: Science/Research
Classifier: Operating System :: OS Independent
Classifier: Programming Language :: Python
Classifier: Programming Language :: Python :: 3
Classifier: Programming Language :: Python :: 3 :: Only
Classifier: Programming Language :: Python :: 3.10
Classifier: Programming Language :: Python :: 3.11
Classifier: Programming Language :: Python :: 3.12
Classifier: Programming Language :: Python :: 3.13
Classifier: Topic :: Software Development :: Libraries
Classifier: Topic :: Software Development :: Libraries :: Python Modules
Classifier: Topic :: Scientific/Engineering
Classifier: Topic :: Scientific/Engineering :: Astronomy
Requires-Python: >=3.10
License-File: LICENSE
Requires-Dist: numpy
Requires-Dist: pyzmq>=24
Requires-Dist: h5py>=3.1.0
Requires-Dist: prometheus-client
Dynamic: license-file
